{
  "captures": [
    {
      "state": "default",
      "label": "sort materials",
      "action": "sortMaterials",
      "file": "01-sort-materials.png",
      "path": "/Users/sbrooker/repos/Bubble-Boy/reports/toybox-animation-review/2026-06-23/camp-storage-sitting/01-sort-materials.png",
      "url": "http://127.0.0.1:8765/toybox?reviewFamily=campStorageSitting&reviewState=default&captureBust=1782193519116",
      "evidence": {
        "animationClip": "Sitting",
        "animationRootMotion": "false",
        "animationSemanticAction": "sortMaterials",
        "attachment": "storageMaterial",
        "attachmentSourceId": "procedural_storage_material_attachment",
        "attachmentTransformId": "storageMaterial",
        "boot": "",
        "bubbleBoyAction": "sortMaterials",
        "bubbleBoyGoal": "storage",
        "bubbleBoyPosition": "-4.72,0.20,-1.54",
        "buildPlankHeldVisible": "false",
        "buildRopeHeldVisible": "false",
        "campPathsActive": "false",
        "campStorageVisible": "true",
        "campStorageWoodCount": "5.00",
        "canvasSize": {
          "height": 1440,
          "width": 2560
        },
        "emoteOverlay": "sortMaterials",
        "emoteRootMotion": "false",
        "firstFireActive": "",
        "firstToolHeldVisible": "false",
        "lastError": "",
        "locomotionOverlay": "",
        "locomotionRootMotion": "false",
        "proceduralOverlay": "sortMaterials",
        "restShelterActive": "false",
        "reviewFamily": "campStorageSitting",
        "reviewPresentationAction": "sortMaterials",
        "reviewState": "default",
        "selectedAction": "sortMaterials",
        "storageMaterialHeldVisible": "true",
        "storageWorkbenchToolsStage": "sorting",
        "storageWorkbenchToolsVariant": "campStorageSorting"
      }
    },
    {
      "state": "depositStorage",
      "label": "deposit storage",
      "action": "depositStorage",
      "file": "02-deposit-storage.png",
      "path": "/Users/sbrooker/repos/Bubble-Boy/reports/toybox-animation-review/2026-06-23/camp-storage-sitting/02-deposit-storage.png",
      "url": "http://127.0.0.1:8765/toybox?reviewFamily=campStorageSitting&reviewState=depositStorage&captureBust=1782193525171",
      "evidence": {
        "animationClip": "Idle",
        "animationRootMotion": "false",
        "animationSemanticAction": "depositStorage",
        "attachment": "storageMaterial",
        "attachmentSourceId": "procedural_storage_material_attachment",
        "attachmentTransformId": "storageMaterial",
        "boot": "",
        "bubbleBoyAction": "depositStorage",
        "bubbleBoyGoal": "storage",
        "bubbleBoyPosition": "-4.72,0.20,-1.54",
        "buildPlankHeldVisible": "false",
        "buildRopeHeldVisible": "false",
        "campPathsActive": "false",
        "campStorageVisible": "true",
        "campStorageWoodCount": "6.00",
        "canvasSize": {
          "height": 1440,
          "width": 2560
        },
        "emoteOverlay": "depositStorage",
        "emoteRootMotion": "false",
        "firstFireActive": "",
        "firstToolHeldVisible": "false",
        "lastError": "",
        "locomotionOverlay": "",
        "locomotionRootMotion": "false",
        "proceduralOverlay": "depositStorage",
        "restShelterActive": "false",
        "reviewFamily": "campStorageSitting",
        "reviewPresentationAction": "depositStorage",
        "reviewState": "watering",
        "selectedAction": "depositStorage",
        "storageMaterialHeldVisible": "true",
        "storageWorkbenchToolsStage": "depositStorage",
        "storageWorkbenchToolsVariant": "campStorageSorting"
      }
    },
    {
      "state": "withdrawStorage",
      "label": "withdraw storage",
      "action": "withdrawStorage",
      "file": "03-withdraw-storage.png",
      "path": "/Users/sbrooker/repos/Bubble-Boy/reports/toybox-animation-review/2026-06-23/camp-storage-sitting/03-withdraw-storage.png",
      "url": "http://127.0.0.1:8765/toybox?reviewFamily=campStorageSitting&reviewState=withdrawStorage&captureBust=1782193528105",
      "evidence": {
        "animationClip": "Idle",
        "animationRootMotion": "false",
        "animationSemanticAction": "withdrawStorage",
        "attachment": "storageMaterial",
        "attachmentSourceId": "procedural_storage_material_attachment",
        "attachmentTransformId": "storageMaterial",
        "boot": "",
        "bubbleBoyAction": "withdrawStorage",
        "bubbleBoyGoal": "storage",
        "bubbleBoyPosition": "-4.72,0.20,-1.54",
        "buildPlankHeldVisible": "false",
        "buildRopeHeldVisible": "false",
        "campPathsActive": "false",
        "campStorageVisible": "true",
        "campStorageWoodCount": "5.00",
        "canvasSize": {
          "height": 1440,
          "width": 2560
        },
        "emoteOverlay": "withdrawStorage",
        "emoteRootMotion": "false",
        "firstFireActive": "",
        "firstToolHeldVisible": "false",
        "lastError": "",
        "locomotionOverlay": "",
        "locomotionRootMotion": "false",
        "proceduralOverlay": "withdrawStorage",
        "restShelterActive": "false",
        "reviewFamily": "campStorageSitting",
        "reviewPresentationAction": "withdrawStorage",
        "reviewState": "variant",
        "selectedAction": "withdrawStorage",
        "storageMaterialHeldVisible": "true",
        "storageWorkbenchToolsStage": "withdrawStorage",
        "storageWorkbenchToolsVariant": "campStorageSorting"
      }
    },
    {
      "state": "tidyCamp",
      "label": "tidy camp",
      "action": "tidyCamp",
      "file": "04-tidy-camp.png",
      "path": "/Users/sbrooker/repos/Bubble-Boy/reports/toybox-animation-review/2026-06-23/camp-storage-sitting/04-tidy-camp.png",
      "url": "http://127.0.0.1:8765/toybox?reviewFamily=campStorageSitting&reviewState=tidyCamp&captureBust=1782193530637",
      "evidence": {
        "animationClip": "Idle",
        "animationRootMotion": "false",
        "animationSemanticAction": "tidyCamp",
        "attachment": "",
        "attachmentSourceId": "",
        "attachmentTransformId": "",
        "boot": "",
        "bubbleBoyAction": "tidyCamp",
        "bubbleBoyGoal": "tidyCamp",
        "bubbleBoyPosition": "-3.48,0.20,-1.34",
        "buildPlankHeldVisible": "false",
        "buildRopeHeldVisible": "false",
        "campPathsActive": "false",
        "campStorageVisible": "true",
        "campStorageWoodCount": "5.00",
        "canvasSize": {
          "height": 1440,
          "width": 2560
        },
        "emoteOverlay": "tidyCamp",
        "emoteRootMotion": "false",
        "firstFireActive": "",
        "firstToolHeldVisible": "false",
        "lastError": "",
        "locomotionOverlay": "",
        "locomotionRootMotion": "false",
        "proceduralOverlay": "tidyCamp",
        "restShelterActive": "false",
        "reviewFamily": "campStorageSitting",
        "reviewPresentationAction": "tidyCamp",
        "reviewState": "debug",
        "selectedAction": "tidyCamp",
        "storageMaterialHeldVisible": "false",
        "storageWorkbenchToolsStage": "tidying",
        "storageWorkbenchToolsVariant": "campStorageSorting"
      }
    },
    {
      "state": "sitNearFire",
      "label": "sit near fire",
      "action": "sitNearFire",
      "file": "05-sit-near-fire.png",
      "path": "/Users/sbrooker/repos/Bubble-Boy/reports/toybox-animation-review/2026-06-23/camp-storage-sitting/05-sit-near-fire.png",
      "url": "http://127.0.0.1:8765/toybox?reviewFamily=campStorageSitting&reviewState=sitNearFire&captureBust=1782193533290",
      "evidence": {
        "animationClip": "Sitting",
        "animationRootMotion": "false",
        "animationSemanticAction": "sitNearFire",
        "attachment": "",
        "attachmentSourceId": "",
        "attachmentTransformId": "",
        "boot": "",
        "bubbleBoyAction": "sitNearFire",
        "bubbleBoyGoal": "reflection",
        "bubbleBoyPosition": "-0.38,0.20,0.82",
        "buildPlankHeldVisible": "false",
        "buildRopeHeldVisible": "false",
        "campPathsActive": "false",
        "campStorageVisible": "true",
        "campStorageWoodCount": "5.00",
        "canvasSize": {
          "height": 1440,
          "width": 2560
        },
        "emoteOverlay": "sitNearFire",
        "emoteRootMotion": "false",
        "firstFireActive": "",
        "firstToolHeldVisible": "false",
        "lastError": "",
        "locomotionOverlay": "",
        "locomotionRootMotion": "false",
        "proceduralOverlay": "sitNearFire",
        "restShelterActive": "true",
        "reviewFamily": "campStorageSitting",
        "reviewPresentationAction": "sitNearFire",
        "reviewState": "closeup",
        "selectedAction": "sitNearFire",
        "storageMaterialHeldVisible": "false",
        "storageWorkbenchToolsStage": "toolReady",
        "storageWorkbenchToolsVariant": "workbenchStorageRack"
      }
    },
    {
      "state": "inspectCampLayout",
      "label": "inspect camp layout",
      "action": "inspectCampLayout",
      "file": "06-inspect-camp-layout.png",
      "path": "/Users/sbrooker/repos/Bubble-Boy/reports/toybox-animation-review/2026-06-23/camp-storage-sitting/06-inspect-camp-layout.png",
      "url": "http://127.0.0.1:8765/toybox?reviewFamily=campStorageSitting&reviewState=inspectCampLayout&captureBust=1782193535865",
      "evidence": {
        "animationClip": "Idle",
        "animationRootMotion": "false",
        "animationSemanticAction": "inspectCampLayout",
        "attachment": "",
        "attachmentSourceId": "",
        "attachmentTransformId": "",
        "boot": "",
        "bubbleBoyAction": "inspectCampLayout",
        "bubbleBoyGoal": "campLayout",
        "bubbleBoyPosition": "-3.05,0.20,-1.20",
        "buildPlankHeldVisible": "false",
        "buildRopeHeldVisible": "false",
        "campPathsActive": "true",
        "campStorageVisible": "true",
        "campStorageWoodCount": "5.00",
        "canvasSize": {
          "height": 1440,
          "width": 2560
        },
        "emoteOverlay": "inspectCampLayout",
        "emoteRootMotion": "false",
        "firstFireActive": "",
        "firstToolHeldVisible": "false",
        "lastError": "",
        "locomotionOverlay": "turnInPlace",
        "locomotionRootMotion": "false",
        "proceduralOverlay": "inspectCampLayout",
        "restShelterActive": "false",
        "reviewFamily": "campStorageSitting",
        "reviewPresentationAction": "inspectCampLayout",
        "reviewState": "inspection",
        "selectedAction": "inspectCampLayout",
        "storageMaterialHeldVisible": "false",
        "storageWorkbenchToolsStage": "toolReady",
        "storageWorkbenchToolsVariant": "workbenchStorageRack"
      }
    },
    {
      "state": "restInsideShelter",
      "label": "rest inside shelter",
      "action": "restInsideShelter",
      "file": "07-rest-inside-shelter.png",
      "path": "/Users/sbrooker/repos/Bubble-Boy/reports/toybox-animation-review/2026-06-23/camp-storage-sitting/07-rest-inside-shelter.png",
      "url": "http://127.0.0.1:8765/toybox?reviewFamily=campStorageSitting&reviewState=restInsideShelter&captureBust=1782193539367",
      "evidence": {
        "animationClip": "Sitting",
        "animationRootMotion": "false",
        "animationSemanticAction": "restInsideShelter",
        "attachment": "",
        "attachmentSourceId": "",
        "attachmentTransformId": "",
        "boot": "",
        "bubbleBoyAction": "restInsideShelter",
        "bubbleBoyGoal": "rest",
        "bubbleBoyPosition": "-5.84,0.20,-2.60",
        "buildPlankHeldVisible": "false",
        "buildRopeHeldVisible": "false",
        "campPathsActive": "false",
        "campStorageVisible": "true",
        "campStorageWoodCount": "5.00",
        "canvasSize": {
          "height": 1440,
          "width": 2560
        },
        "emoteOverlay": "restInsideShelter",
        "emoteRootMotion": "false",
        "firstFireActive": "",
        "firstToolHeldVisible": "false",
        "lastError": "",
        "locomotionOverlay": "",
        "locomotionRootMotion": "false",
        "proceduralOverlay": "restInsideShelter",
        "restShelterActive": "true",
        "reviewFamily": "campStorageSitting",
        "reviewPresentationAction": "restInsideShelter",
        "reviewState": "complete",
        "selectedAction": "restInsideShelter",
        "storageMaterialHeldVisible": "false",
        "storageWorkbenchToolsStage": "toolReady",
        "storageWorkbenchToolsVariant": "workbenchStorageRack"
      }
    }
  ],
  "console": []
}